setup.cfg
setup.py
mwstools/__init__.py
mwstools/mws_overrides.py
mwstools/utils.py
mwstools/parsers/__init__.py
mwstools/parsers/base.py
mwstools/parsers/errors.py
mwstools/parsers/feeds.py
mwstools/parsers/get_service_status.py
mwstools/parsers/notifications.py
mwstools/parsers/orders.py
mwstools/parsers/reports.py
mwstools/parsers/products/__init__.py
mwstools/parsers/products/base.py
mwstools/parsers/products/errors.py
mwstools/parsers/products/get_competitive_pricing_for_asin.py
mwstools/parsers/products/get_lowest_offer_listings_for_asin.py
mwstools/parsers/products/get_matching_product_for_id.py
mwstools/parsers/products/get_my_fees_estimate.py
mwstools/parsers/products/get_my_price_for_sku.py
mwstools/requesters/__init__.py
mwstools/requesters/base.py
mwstools/requesters/orders.py
mwstools/requesters/products.py
mwstools/requesters/reports.py
mwstools/requesters/utils.py
python_amazon_mws_tools.egg-info/PKG-INFO
python_amazon_mws_tools.egg-info/SOURCES.txt
python_amazon_mws_tools.egg-info/dependency_links.txt
python_amazon_mws_tools.egg-info/requires.txt
python_amazon_mws_tools.egg-info/top_level.txt
tests/__init__.py
tests/test_misc.py
tests/tests.py
tests/parsers/__init__.py
tests/parsers/test_ErrorResponse.py
tests/parsers/feeds/__init__.py
tests/parsers/feeds/test_FeedSubmissionInfo.py
tests/parsers/feeds/test_GetFeedSubmissionListResponse.py
tests/parsers/feeds/test_SubmitFeedResponse.py
tests/parsers/feeds/test_all.py
tests/parsers/misc/__init__.py
tests/parsers/misc/test_GetServiceStatusResponse.py
tests/parsers/misc/test_all.py
tests/parsers/notifications/__init__.py
tests/parsers/notifications/test_AnyOfferChangedNotification.py
tests/parsers/notifications/test_BuyBoxPrice.py
tests/parsers/notifications/test_LowestPrice.py
tests/parsers/notifications/test_Notification.py
tests/parsers/notifications/test_NotificationMetadata.py
tests/parsers/notifications/test_Offer.py
tests/parsers/notifications/test_OfferChangeTrigger.py
tests/parsers/notifications/test_OfferCount.py
tests/parsers/notifications/test_all.py
tests/parsers/orders/__init__.py
tests/parsers/orders/test_ListOrderItemsResponse.py
tests/parsers/orders/test_ListOrdersResponse.py
