Metadata-Version: 1.0
Name: python-amazon-mws-tools
Version: 0.0.0
Summary: Wrapper modules to request and parse responses for python-amazon-mws.
Home-page: https://github.com/ziplokk1/python-amazon-mws-tools
Author: Mark Sanders
Author-email: sdscdeveloper@gmail.com
License: LICENSE.txt
Platform: UNKNOWN
